Metadata-Version: 2.1
Name: LeBot
Version: 3.5.14.dev1
Summary: A Multi-Purpose Discord Bot
Home-page: https://github.com/LeDeathAmongst/LeBot
Author: Star
Author-email: skylar.rae.val@proton.me
License: UNKNOWN
Platform: UNKNOWN
Classifier: Programming Language :: Python :: 3
Classifier: Operating System :: OS Independent
Requires-Python: >=3.9.1
Requires-Dist: aiohttp-json-rpc==0.13.3
Requires-Dist: aiohttp==3.9.5
Requires-Dist: aiosignal==1.3.1
Requires-Dist: apsw==3.46.1.0
Requires-Dist: attrs==24.2.0
Requires-Dist: babel==2.16.0
Requires-Dist: brotli==1.1.0
Requires-Dist: click==8.1.7
Requires-Dist: discord-py==2.4.0
Requires-Dist: frozenlist==1.4.1
Requires-Dist: idna==3.8
Requires-Dist: markdown-it-py==3.0.0
Requires-Dist: markdown==3.7
Requires-Dist: mdurl==0.1.2
Requires-Dist: multidict==6.0.5
Requires-Dist: orjson==3.10.7
Requires-Dist: packaging==24.1
Requires-Dist: platformdirs==4.2.2
Requires-Dist: psutil==6.0.0
Requires-Dist: pygments==2.18.0
Requires-Dist: python-dateutil==2.9.0.post0
Requires-Dist: pyyaml==6.0.2
Requires-Dist: rapidfuzz==3.9.6
Requires-Dist: red-commons==1.0.0
Requires-Dist: red-lavalink==0.11.0
Requires-Dist: rich==13.8.0
Requires-Dist: schema==0.7.7
Requires-Dist: six==1.16.0
Requires-Dist: typing-extensions==4.12.2
Requires-Dist: yarl==1.9.4
Requires-Dist: uvloop==0.20.0; (sys_platform != "win32" and platform_python_implementation == "CPython") and sys_platform != "win32"
Requires-Dist: importlib-metadata==8.4.0; python_version != "3.10" and python_version != "3.11"
Requires-Dist: zipp==3.20.1; python_version != "3.10" and python_version != "3.11"
Requires-Dist: async-timeout==4.0.3; python_version != "3.11"
Requires-Dist: pytz==2024.1; python_version == "3.8"
Requires-Dist: distro==1.9.0; sys_platform == "linux" and sys_platform == "linux"
Requires-Dist: colorama==0.4.6; sys_platform == "win32"
Provides-Extra: all
Requires-Dist: async-timeout==4.0.3; extra == "all"
Requires-Dist: asyncpg==0.29.0; extra == "all"
Provides-Extra: dev
Requires-Dist: alabaster==0.7.13; extra == "dev"
Requires-Dist: astroid==3.2.4; extra == "dev"
Requires-Dist: async-timeout==4.0.3; extra == "dev"
Requires-Dist: asyncpg==0.29.0; extra == "dev"
Requires-Dist: black==23.12.1; extra == "dev"
Requires-Dist: certifi==2024.7.4; extra == "dev"
Requires-Dist: charset-normalizer==3.3.2; extra == "dev"
Requires-Dist: dill==0.3.8; extra == "dev"
Requires-Dist: docutils==0.20.1; extra == "dev"
Requires-Dist: imagesize==1.4.1; extra == "dev"
Requires-Dist: importlib-metadata==8.4.0; extra == "dev"
Requires-Dist: iniconfig==2.0.0; extra == "dev"
Requires-Dist: isort==5.13.2; extra == "dev"
Requires-Dist: jinja2==3.1.4; extra == "dev"
Requires-Dist: markupsafe==2.1.5; extra == "dev"
Requires-Dist: mccabe==0.7.0; extra == "dev"
Requires-Dist: mypy-extensions==1.0.0; extra == "dev"
Requires-Dist: pathspec==0.12.1; extra == "dev"
Requires-Dist: pluggy==1.5.0; extra == "dev"
Requires-Dist: pylint==3.2.6; extra == "dev"
Requires-Dist: pytest-asyncio==0.21.2; extra == "dev"
Requires-Dist: pytest-mock==3.14.0; extra == "dev"
Requires-Dist: pytest==7.4.4; extra == "dev"
Requires-Dist: pytz==2024.1; extra == "dev"
Requires-Dist: requests==2.32.3; extra == "dev"
Requires-Dist: snowballstemmer==2.2.0; extra == "dev"
Requires-Dist: sphinx-prompt==1.7.0; extra == "dev"
Requires-Dist: sphinx-rtd-theme==2.0.0; extra == "dev"
Requires-Dist: sphinx==7.1.2; extra == "dev"
Requires-Dist: sphinxcontrib-applehelp==1.0.4; extra == "dev"
Requires-Dist: sphinxcontrib-devhelp==1.0.2; extra == "dev"
Requires-Dist: sphinxcontrib-htmlhelp==2.0.1; extra == "dev"
Requires-Dist: sphinxcontrib-jquery==4.1; extra == "dev"
Requires-Dist: sphinxcontrib-jsmath==1.0.1; extra == "dev"
Requires-Dist: sphinxcontrib-qthelp==1.0.3; extra == "dev"
Requires-Dist: sphinxcontrib-serializinghtml==1.1.5; extra == "dev"
Requires-Dist: sphinxcontrib-trio==1.1.2; extra == "dev"
Requires-Dist: tomli==2.0.1; extra == "dev"
Requires-Dist: tomlkit==0.13.2; extra == "dev"
Requires-Dist: urllib3==2.2.2; extra == "dev"
Requires-Dist: zipp==3.20.1; extra == "dev"
Requires-Dist: exceptiongroup==1.2.2; python_version != "3.11" and extra == "dev"
Requires-Dist: tomli==2.0.1; python_version != "3.11" and extra == "dev"
Provides-Extra: doc
Requires-Dist: alabaster==0.7.13; extra == "doc"
Requires-Dist: certifi==2024.7.4; extra == "doc"
Requires-Dist: charset-normalizer==3.3.2; extra == "doc"
Requires-Dist: docutils==0.20.1; extra == "doc"
Requires-Dist: imagesize==1.4.1; extra == "doc"
Requires-Dist: importlib-metadata==8.4.0; extra == "doc"
Requires-Dist: jinja2==3.1.4; extra == "doc"
Requires-Dist: markupsafe==2.1.5; extra == "doc"
Requires-Dist: pytz==2024.1; extra == "doc"
Requires-Dist: requests==2.32.3; extra == "doc"
Requires-Dist: snowballstemmer==2.2.0; extra == "doc"
Requires-Dist: sphinx-prompt==1.7.0; extra == "doc"
Requires-Dist: sphinx-rtd-theme==2.0.0; extra == "doc"
Requires-Dist: sphinx==7.1.2; extra == "doc"
Requires-Dist: sphinxcontrib-applehelp==1.0.4; extra == "doc"
Requires-Dist: sphinxcontrib-devhelp==1.0.2; extra == "doc"
Requires-Dist: sphinxcontrib-htmlhelp==2.0.1; extra == "doc"
Requires-Dist: sphinxcontrib-jquery==4.1; extra == "doc"
Requires-Dist: sphinxcontrib-jsmath==1.0.1; extra == "doc"
Requires-Dist: sphinxcontrib-qthelp==1.0.3; extra == "doc"
Requires-Dist: sphinxcontrib-serializinghtml==1.1.5; extra == "doc"
Requires-Dist: sphinxcontrib-trio==1.1.2; extra == "doc"
Requires-Dist: urllib3==2.2.2; extra == "doc"
Requires-Dist: zipp==3.20.1; extra == "doc"
Provides-Extra: postgres
Requires-Dist: async-timeout==4.0.3; extra == "postgres"
Requires-Dist: asyncpg==0.29.0; extra == "postgres"
Provides-Extra: style
Requires-Dist: black==23.12.1; extra == "style"
Requires-Dist: mypy-extensions==1.0.0; extra == "style"
Requires-Dist: pathspec==0.12.1; extra == "style"
Requires-Dist: tomli==2.0.1; extra == "style"
Provides-Extra: test
Requires-Dist: astroid==3.2.4; extra == "test"
Requires-Dist: dill==0.3.8; extra == "test"
Requires-Dist: iniconfig==2.0.0; extra == "test"
Requires-Dist: isort==5.13.2; extra == "test"
Requires-Dist: mccabe==0.7.0; extra == "test"
Requires-Dist: pluggy==1.5.0; extra == "test"
Requires-Dist: pylint==3.2.6; extra == "test"
Requires-Dist: pytest-asyncio==0.21.2; extra == "test"
Requires-Dist: pytest-mock==3.14.0; extra == "test"
Requires-Dist: pytest==7.4.4; extra == "test"
Requires-Dist: tomlkit==0.13.2; extra == "test"
Requires-Dist: exceptiongroup==1.2.2; python_version != "3.11" and extra == "test"
Requires-Dist: tomli==2.0.1; python_version != "3.11" and extra == "test"
